infinity_coin/__init__.py
infinity_coin/exceptions.py
infinity_coin/infinity_coin.py
infinity_coin/longpoll.py
infinity_coin-1.2.dist-info/LICENSE
infinity_coin-1.2.dist-info/METADATA
infinity_coin-1.2.dist-info/WHEEL
infinity_coin-1.2.dist-info/top_level.txt
infinity_coin-1.2.dist-info/RECORD
