Metadata-Version: 2.1
Name: infinity-coin
Version: 1.2
Summary: infinity_coin - это python модуль для работы с монетой Infinity Сoin (Infinity Сoin API wrapper)
Home-page: https://github.com/MrSmitix/infinity_coin
Author: MrSmitix
Author-email: mr.smitix@gmail.com
License: Apache License, Version 2.0, see LICENSE file
Download-URL: https://github.com/MrSmitix/infinity_coin/archive/v1.2.zip
Platform: UNKNOWN
Classifier: License :: OSI Approved :: Apache Software License
Classifier: Operating System :: OS Independent
Classifier: Programming Language :: Python
Classifier: Programming Language :: Python :: 3.6
Classifier: Programming Language :: Python :: 3.7
Classifier: Programming Language :: Python :: Implementation :: PyPy
Classifier: Programming Language :: Python :: Implementation :: CPython
Requires-Dist: requests
